{
  "id": "vehicle-image-library",
  "name": "vehicle-image-library",
  "title": "车型图库与人工标签",
  "description": "",
  "status": "in_progress",
  "dev_type": null,
  "scope": null,
  "package": null,
  "priority": "P2",
  "creator": "codex",
  "assignee": "codex",
  "createdAt": "2026-07-23",
  "completedAt": null,
  "branch": null,
  "base_branch": "main",
  "worktree_path": null,
  "commit": null,
  "pr_url": null,
  "subtasks": [],
  "children": [],
  "parent": null,
  "relatedFiles": [],
  "notes": "Local implementation, independent review, full baseline, local restart, and mocked desktop/mobile browser verification complete. Keep in progress because the reference-library base and shared files contain pre-existing uncommitted work that cannot be isolated into a clean Phase 3.4 commit.",
  "meta": {}
}
